App/__init__.py
App/__main__.py
App/app.py
App/routes.py
App/static/style.css
App/static/styles.css
App/templates/index.html
App/templates/quiz.html
App/templates/result.html
App/templates/scores.html
App/templates/start_quiz.html
App/templates/view_scores.html
vocabulary_quiz-0.6.dist-info/METADATA
vocabulary_quiz-0.6.dist-info/WHEEL
vocabulary_quiz-0.6.dist-info/entry_points.txt
vocabulary_quiz-0.6.dist-info/top_level.txt
vocabulary_quiz-0.6.dist-info/RECORD
