Metadata-Version: 2.1
Name: vocabulary-quiz
Version: 0.6
Requires-Dist: flask
Requires-Dist: requests
Requires-Dist: beautifulsoup4
